Workbook

Sheet Mapa de procesos
A1: MAPA DE PROCESOS
A2: (pegue en esta pestaña su mapa de procesos)

Sheet Matriz
B1: MATRIZ DE RIESGOS Y OPORTUNIDADES | G1: N° VERSION: 07
A2: REF: F-GC-08 | G2: Fecha de vigencia: 18/02/2026
A3: ELABORADO | B3: REVISADO | G3: APROBADO
A4: Analista de Calidad | B4: Coordinador de Calidad | G4: Coordinador de Calidad
A5: Documento de carácter RESERVADO. Su contenido es de uso interno. Se prohíbe su divulgación a terceros sin autorización expresa de Manzur Administraciones
A6: Fecha de última actualización de la matriz: | C6: 46099
A7: IDENTIFICACIÓN Y EVALUACIÓN | I7: PLANIFICACIÓN | O7: SEGUIMIENTO | T7: EFICACIA | V7: EVALUACIÓN DE RIESGO RESIDUAL
A8: Área | B8: Proceso | C8: Descripción del Riesgo u Oportunidad | D8: Descripción de la consecuencia | E8: Tipo: Riesgo/ Oportunidad | F8: Probabilidad de que ocurra | G8: Impacto que tendría si ocurre | H8: Criticidad | I8: Acciones | J8: Responsable | K8: Recursos | L8: Fecha comienzo | M8: Fecha fin | N8: Periodicidad de seguimiento | O8: Estado de las acciones | P8: PRIMER TRIMESTRE | Q8: SEGUNDO TRIMESTRE | R8: TERCER TRIMESTRE | S8: CUARTO TRIMESTRE | T8: Resultado observado | U8: Declaración de eficacia | V8: Probabilidad de que ocurra2 | W8: Impacto que tendría si ocurre2 | X8: Criticidad2 | Y8: Recomendación del SGC (mensaje automático)
A9: SISTEMAS | B9: Gestión de cambios tecnológicos | C9: Mejora de conectividad en sucursales del norte | D9: Facturación en tiempo real; Aumento de productividad | E9: Oportunidad | F9: Muy posible | G9: Alto impacto | H9: {=_xlfn.XLOOKUP( 1, (Matriz!F9=Referencias!$A$19:$A$28)*(Matriz!G9=Referencias!$B$19:$B$28), Referencias!$C$19:$C$28, "" )} -> Alta | I9: *Realización de pruebas de conectividad con Starlink *Análisis de resultados del testeo *Contratación del servicio Starlink | J9: Equipo de Sistemas | K9: Horas hombre Contratación de Servicio Starlink en reemplazo del proveedor actual | L9: 46116 | M9: 46387 | N9: Semestral | O9: No iniciado | X9: {=_xlfn.XLOOKUP( 1, (Matriz!V9=Referencias!$A$19:$A$28)*(Matriz!W9=Referencias!$B$19:$B$28), Referencias!$C$19:$C$28, "" )} | Y9: =IFERROR(IF( E9="Riesgo", VLOOKUP(Tabla1[[#This Row],[Criticidad2]], Referencias!$A$47:$B$49, 2, FALSE), IF( AND(E9="Oportunidad", U9="No eficaz"), VLOOKUP(U9, Referencias!$A$50:$B$50, 2, FALSE), "" ) ),"")
A10: SISTEMAS | B10: Gestión de cambios tecnológicos | C10: Falta de información precisa y actualizada sobre el inventario de equipos y dispositivos asignados a los colaboradores. | D10: Falta de claridad sobre la cantidad y estado de los equipos o dispositivos asignados; Dificultad o demoras en la obtención de información actualizada del inventario cuando es requerida; Posibles inconsistencias entre los registros y la disponibilidad real de los activos. | E10: Riesgo | F10: Muy posible | G10: Medio impacto | H10: {=_xlfn.XLOOKUP( 1, (Matriz!F10=Referencias!$A$19:$A$28)*(Matriz!G10=Referencias!$B$19:$B$28), Referencias!$C$19:$C$28, "" )} -> Alta | I10: *Evaluación y selección de un sistema de gestión de inventario adecuado a las necesidades de la organización. *Actualización y regularización del inventario de equipos y dispositivos. *Control de equipos y dispositivos de inventario durante visitas a sucursales. | J10: Equipo de Sistemas | K10: Horas hombre | L10: 45782 | M10: 46142 | N10: Anual | O10: En proceso | X10: {=_xlfn.XLOOKUP( 1, (Matriz!V10=Referencias!$A$19:$A$28)*(Matriz!W10=Referencias!$B$19:$B$28), Referencias!$C$19:$C$28, "" )} | Y10: =IFERROR(IF( E10="Riesgo", VLOOKUP(Tabla1[[#This Row],[Criticidad2]], Referencias!$A$47:$B$49, 2, FALSE), IF( AND(E10="Oportunidad", U10="No eficaz"), VLOOKUP(U10, Referencias!$A$50:$B$50, 2, FALSE), "" ) ),"")
A11: SISTEMAS | B11: Seguridad tecnológica | C11: Posibles vulnerabilidades frente a amenazas de ciberseguridad | D11: Robo de datos sensibles, confidenciales o estratégicos; Posible eliminación o encriptación de la información que puede ocasionar costos de recuperación de datos; Pérdida de ingresos por interrupción de operaciones | E11: Riesgo | F11: Muy posible | G11: Alto impacto | H11: {=_xlfn.XLOOKUP( 1, (Matriz!F11=Referencias!$A$19:$A$28)*(Matriz!G11=Referencias!$B$19:$B$28), Referencias!$C$19:$C$28, "" )} -> Alta | I11: Realizar la búsqueda y selección de personal especializado en ciberseguridad para su posterior contratación o asesoramiento, con el objetivo de evaluar las vulnerabilidades existentes y definir una metodología de trabajo en seguridad de la información. | J11: Facundo Ainstein | K11: Horas hombre Pago al especialista | L11: 45782 | M11: 46203 | N11: Anual | O11: En proceso | X11: {=_xlfn.XLOOKUP( 1, (Matriz!V11=Referencias!$A$19:$A$28)*(Matriz!W11=Referencias!$B$19:$B$28), Referencias!$C$19:$C$28, "" )} | Y11: =IFERROR(IF( E11="Riesgo", VLOOKUP(Tabla1[[#This Row],[Criticidad2]], Referencias!$A$47:$B$49, 2, FALSE), IF( AND(E11="Oportunidad", U11="No eficaz"), VLOOKUP(U11, Referencias!$A$50:$B$50, 2, FALSE), "" ) ),"")
A12: SISTEMAS | B12: Gestión de cambios tecnológicos | C12: Alto costo del proveedor de internet secundario en Badie Salta, con desempeño ineficiente del servicio | D12: Indisponibilidad de servicio a internet cuando se lo requiera; Posibles afectaciones a la operatoria; Afectación a la productividad | E12: Riesgo | F12: Muy posible | G12: Medio impacto | H12: {=_xlfn.XLOOKUP( 1, (Matriz!F12=Referencias!$A$19:$A$28)*(Matriz!G12=Referencias!$B$19:$B$28), Referencias!$C$19:$C$28, "" )} -> Alta | I12: Evaluar y cambiar el proveedor secundario en Badie Salta, Starlink y Failover con Corbalan | J12: Facundo Ainstein | K12: Horas hombre Pago al especialista | L12: 46118 | M12: 46203 | N12: Anual | O12: No iniciado | X12: {=_xlfn.XLOOKUP( 1, (Matriz!V12=Referencias!$A$19:$A$28)*(Matriz!W12=Referencias!$B$19:$B$28), Referencias!$C$19:$C$28, "" )} | Y12: =IFERROR(IF( E12="Riesgo", VLOOKUP(Tabla1[[#This Row],[Criticidad2]], Referencias!$A$47:$B$49, 2, FALSE), IF( AND(E12="Oportunidad", U12="No eficaz"), VLOOKUP(U12, Referencias!$A$50:$B$50, 2, FALSE), "" ) ),"")
A13: SISTEMAS | B13: Infraestructura | C13: El servidor que aloja las bases de Chess y Bejerman presenta falta de recursos de hardware | D13: Lentitud en el acceso a los sistemas y riesgo de fallas durante procesos críticos de operación | E13: Riesgo | F13: Muy posible | G13: Alto impacto | H13: {=_xlfn.XLOOKUP( 1, (Matriz!F13=Referencias!$A$19:$A$28)*(Matriz!G13=Referencias!$B$19:$B$28), Referencias!$C$19:$C$28, "" )} -> Alta | I13: Ampliar capacidad de almacenamiento y memoria RAM del servidor | J13: Leonardo Campos | K13: Compra de disco y memoria | L13: 45782 | M13: 46112 | N13: Anual | O13: En proceso | X13: {=_xlfn.XLOOKUP( 1, (Matriz!V13=Referencias!$A$19:$A$28)*(Matriz!W13=Referencias!$B$19:$B$28), Referencias!$C$19:$C$28, "" )} | Y13: =IFERROR(IF( E13="Riesgo", VLOOKUP(Tabla1[[#This Row],[Criticidad2]], Referencias!$A$47:$B$49, 2, FALSE), IF( AND(E13="Oportunidad", U13="No eficaz"), VLOOKUP(U13, Referencias!$A$50:$B$50, 2, FALSE), "" ) ),"")
A14: SISTEMAS | B14: Infraestructura | C14: Bajo rendimiento del servidor Don Pedro durante picos de operación | D14: Demoras significativas durante la liquidación de cargas, afectando tiempos operativos | E14: Riesgo | F14: Muy posible | G14: Medio impacto | H14: {=_xlfn.XLOOKUP( 1, (Matriz!F14=Referencias!$A$19:$A$28)*(Matriz!G14=Referencias!$B$19:$B$28), Referencias!$C$19:$C$28, "" )} -> Alta | I14: Migrar la maquina virtual al servidor donde estan alojadas las demas bases o bien mejorar el rendimiento del servidor actual | J14: Leonardo Campos | K14: Compra de memoria en caso de actualizar el servidor | L14: 45810 | M14: 46172 | N14: Anual | O14: En proceso | X14: {=_xlfn.XLOOKUP( 1, (Matriz!V14=Referencias!$A$19:$A$28)*(Matriz!W14=Referencias!$B$19:$B$28), Referencias!$C$19:$C$28, "" )} | Y14: =IFERROR(IF( E14="Riesgo", VLOOKUP(Tabla1[[#This Row],[Criticidad2]], Referencias!$A$47:$B$49, 2, FALSE), IF( AND(E14="Oportunidad", U14="No eficaz"), VLOOKUP(U14, Referencias!$A$50:$B$50, 2, FALSE), "" ) ),"")
A15: SISTEMAS | B15: Infraestructura | C15: Migración del sistema Tango a un servidor con mayores prestaciones | D15: Reducción de tiempos de reinicio y mejora en la estabilidad del sistema | E15: Oportunidad | F15: Algo posible | G15: Medio impacto | H15: {=_xlfn.XLOOKUP( 1, (Matriz!F15=Referencias!$A$19:$A$28)*(Matriz!G15=Referencias!$B$19:$B$28), Referencias!$C$19:$C$28, "" )} -> Media | I15: Migrar la máquina virtual a un servidor de mayor capacidad | J15: Leonardo Campos | K15: Servidor Horas hombre | L15: 45810 | M15: 46172 | N15: Anual | O15: En proceso | X15: {=_xlfn.XLOOKUP( 1, (Matriz!V15=Referencias!$A$19:$A$28)*(Matriz!W15=Referencias!$B$19:$B$28), Referencias!$C$19:$C$28, "" )} | Y15: =IFERROR(IF( E15="Riesgo", VLOOKUP(Tabla1[[#This Row],[Criticidad2]], Referencias!$A$47:$B$49, 2, FALSE), IF( AND(E15="Oportunidad", U15="No eficaz"), VLOOKUP(U15, Referencias!$A$50:$B$50, 2, FALSE), "" ) ),"")
A16: SISTEMAS | B16: Seguridad tecnológica | C16: Vulnerabilidad ante posibles hackeos de cuentas de WhatsApp empresariales | D16: Pérdida de control de cuentas institucionales, envío de comunicaciones fraudulentas a clientes o colaboradores y posible daño reputacional y económico. | E16: Riesgo | F16: Algo posible | G16: Alto impacto | H16: {=_xlfn.XLOOKUP( 1, (Matriz!F16=Referencias!$A$19:$A$28)*(Matriz!G16=Referencias!$B$19:$B$28), Referencias!$C$19:$C$28, "" )} -> Alta | I16: Solicitar que el pedido lo realice directamente un superior y realizar el seguimiento | J16: Facundo Ainstein | K16: Horas Hombre | L16: 46118 | M16: 46233 | N16: Bimestral | O16: No iniciado | X16: {=_xlfn.XLOOKUP( 1, (Matriz!V16=Referencias!$A$19:$A$28)*(Matriz!W16=Referencias!$B$19:$B$28), Referencias!$C$19:$C$28, "" )} | Y16: =IFERROR(IF( E16="Riesgo", VLOOKUP(Tabla1[[#This Row],[Criticidad2]], Referencias!$A$47:$B$49, 2, FALSE), IF( AND(E16="Oportunidad", U16="No eficaz"), VLOOKUP(U16, Referencias!$A$50:$B$50, 2, FALSE), "" ) ),"")
A17: SISTEMAS | B17: Soporte tecnológico | C17: Limitación de licencias gratuitas del sistema Freshdesk (2 gratuitas) | D17: Imposibilita la creacion de usuario para el uso del sistema. Uso de herramienta para futuros ingresos al area o implementacion para otra area | E17: Oportunidad | F17: Algo posible | G17: Bajo impacto | H17: {=_xlfn.XLOOKUP( 1, (Matriz!F17=Referencias!$A$19:$A$28)*(Matriz!G17=Referencias!$B$19:$B$28), Referencias!$C$19:$C$28, "" )} -> Baja | I17: Evaluar contratación de licencias adicionales o migración a una herramienta sin limites de usuarios | J17: Mauro Luna | K17: Contratación de licencias | L17: 46099 | M17: 46203 | N17: Anual | O17: En proceso | X17: {=_xlfn.XLOOKUP( 1, (Matriz!V17=Referencias!$A$19:$A$28)*(Matriz!W17=Referencias!$B$19:$B$28), Referencias!$C$19:$C$28, "" )} | Y17: =IFERROR(IF( E17="Riesgo", VLOOKUP(Tabla1[[#This Row],[Criticidad2]], Referencias!$A$47:$B$49, 2, FALSE), IF( AND(E17="Oportunidad", U17="No eficaz"), VLOOKUP(U17, Referencias!$A$50:$B$50, 2, FALSE), "" ) ),"")
A18: SISTEMAS | B18: Infraestructura | C18: Uso de sistemas operativos de servidores sin soporte o desactualizados | D18: Mayor vulnerabilidad ante virus en servidores; Posibles errores en aplicaciones; Posibles accesos no autorizados; Indisponibilidad de servicios y posible pérdida o alteración de información | E18: Riesgo | F18: Muy posible | G18: Medio impacto | H18: {=_xlfn.XLOOKUP( 1, (Matriz!F18=Referencias!$A$19:$A$28)*(Matriz!G18=Referencias!$B$19:$B$28), Referencias!$C$19:$C$28, "" )} -> Alta | I18: Consultar con proveedores de sistemas Compatibilidad con Sistemas Operativos nuevos Actualización de Sistema Operativos de Servidores | J18: Facundo Ainstein | K18: Horas hombre | L18: 45719 | M18: 46264 | N18: Anual | O18: En proceso | X18: {=_xlfn.XLOOKUP( 1, (Matriz!V18=Referencias!$A$19:$A$28)*(Matriz!W18=Referencias!$B$19:$B$28), Referencias!$C$19:$C$28, "" )} | Y18: =IFERROR(IF( E18="Riesgo", VLOOKUP(Tabla1[[#This Row],[Criticidad2]], Referencias!$A$47:$B$49, 2, FALSE), IF( AND(E18="Oportunidad", U18="No eficaz"), VLOOKUP(U18, Referencias!$A$50:$B$50, 2, FALSE), "" ) ),"")
A19: SISTEMAS | B19: Gestión de cambios tecnológicos | C19: Fuerte dependencia del proveedor Chess y limitaciones de acceso a bases de datos | D19: Dificultad para avanzar en proyectos integrales y dependencia operativa del proveedor | E19: Oportunidad | F19: Muy posible | G19: Medio impacto | H19: {=_xlfn.XLOOKUP( 1, (Matriz!F19=Referencias!$A$19:$A$28)*(Matriz!G19=Referencias!$B$19:$B$28), Referencias!$C$19:$C$28, "" )} -> Alta | I19: *Busqueda de sistemas alternativos a Chess *Demos de los sistemas ofrecidos *Pruebas de sistemas para evaluar pro y contras | J19: Facundo Ainstein | K19: Horas hombre | L19: 45719 | M19: 46172 | N19: Anual | O19: En proceso | X19: {=_xlfn.XLOOKUP( 1, (Matriz!V19=Referencias!$A$19:$A$28)*(Matriz!W19=Referencias!$B$19:$B$28), Referencias!$C$19:$C$28, "" )} | Y19: =IFERROR(IF( E19="Riesgo", VLOOKUP(Tabla1[[#This Row],[Criticidad2]], Referencias!$A$47:$B$49, 2, FALSE), IF( AND(E19="Oportunidad", U19="No eficaz"), VLOOKUP(U19, Referencias!$A$50:$B$50, 2, FALSE), "" ) ),"")
A20: SISTEMAS | B20: Infraestructura | C20: Indisponibilidad de servidores luego de 1 hora de autonomía del UPS | D20: Interrupción del proceso de facturación y detención de operaciones críticas | E20: Riesgo | F20: Algo posible | G20: Alto impacto | H20: {=_xlfn.XLOOKUP( 1, (Matriz!F20=Referencias!$A$19:$A$28)*(Matriz!G20=Referencias!$B$19:$B$28), Referencias!$C$19:$C$28, "" )} -> Alta | I20: Instalación de Grupo Electrogeno en Rack de sistemas | J20: Facundo Ainstein | K20: Compra de grupo Electrogeno Mano de Obra para Instalacion | L20: 46118 | M20: 46203 | N20: Bimestral | O20: No iniciado | X20: {=_xlfn.XLOOKUP( 1, (Matriz!V20=Referencias!$A$19:$A$28)*(Matriz!W20=Referencias!$B$19:$B$28), Referencias!$C$19:$C$28, "" )} | Y20: =IFERROR(IF( E20="Riesgo", VLOOKUP(Tabla1[[#This Row],[Criticidad2]], Referencias!$A$47:$B$49, 2, FALSE), IF( AND(E20="Oportunidad", U20="No eficaz"), VLOOKUP(U20, Referencias!$A$50:$B$50, 2, FALSE), "" ) ),"")
... A35: SISTEMAS | B35: Desarrollo de Software | C35: Desarrollar e implementar un sistema de selección de talentos para RRHH Soft | D35: Poder recibir y administrar un banco de CVs donde se pueda gestionar posibles nuevos ingresos a la empresa. | E35: Oportunidad | F35: Muy posible | G35: Alto impacto | H35: {=_xlfn.XLOOKUP( 1, (Matriz!F35=Referencias!$A$19:$A$28)*(Matriz!G35=Referencias!$B$19:$B$28), Referencias!$C$19:$C$28, "" )} -> Alta | I35: Relevamiento de necesidades. Desarrollar un software a medida en base a las necesidades de RRHH Soft. Implementación | J35: Leonardo Campos | K35: Horas hombre, posible suscripcion a servicio de almacenamiento en la nube | L35: 46071 | M35: 46386 | N35: Mensual | O35: En proceso | X35: {=_xlfn.XLOOKUP( 1, (Matriz!V35=Referencias!$A$19:$A$28)*(Matriz!W35=Referencias!$B$19:$B$28), Referencias!$C$19:$C$28, "" )} | Y35: =IFERROR(IF( E35="Riesgo", VLOOKUP(Tabla1[[#This Row],[Criticidad2]], Referencias!$A$47:$B$49, 2, FALSE), IF( AND(E35="Oportunidad", U35="No eficaz"), VLOOKUP(U35, Referencias!$A$50:$B$50, 2, FALSE), "" ) ),"")

Sheet Referencias
A1: PROBABILIDAD | B1: MUY POSIBLE | C1: Medio | D1: Alto | E1: Alto
B2: ALGO POSIBLE | C2: Baja | D2: Medio | E2: Alto
B3: POCO POSIBLE O IMPROBABLE | C3: Baja | D3: Baja | E3: Medio
C4: BAJO IMPACTO | D4: MEDIO IMPACTO | E4: ALTO IMPACTO
C5: IMPACTO
A7: Referencias:
A8: Probabilidad | B8: Muy posible | C8: Es probable que ocurra y puede repetirse varias veces en el año.
A9: Probabilidad | B9: Algo posible | C9: Puede ocurrir en el desarrollo habitual del proceso, aunque no es frecuente.
A10: Probabilidad | B10: Poco posible o improbable | C10: Ocurre de manera excepcional. No se espera en condiciones normales.
A11: Impacto | B11: Alto impacto | C11: Efecto significativo con consecuencias relevantes para el proceso o los objetivos del proceso.
A12: Impacto | B12: Medio impacto | C12: Efecto apreciable, requiere atención o ajustes.
A13: Impacto | B13: Bajo impacto | C13: Efecto menor, poco perceptible en el desempeño del proceso.
A14: Criticidad | B14: Alta | C14: Requiere acciones formales y seguimiento frecuente. El compromiso del equipo es clave para su gestión efectiva.
A15: Criticidad | B15: Baja | C15: Se podrán definir acciones cuando el equipo considere que su gestión agrega valor al proceso.
A16: Criticidad | B16: Media | C16: Requiere definición de acciones y seguimiento planificado.
A18: Probabilidad | B18: Impacto | C18: Criticidad
A19: Poco posible o improbable | B19: Bajo impacto | C19: Baja
A20: Algo posible | B20: Bajo impacto | C20: Baja
... A28: N/A | B28: N/A | C28: N/A
A30: Áreas
A31: AUDITORÍA INTERNA
A32: AUDITORÍA PROD Y SERV
A33: COMPRAS
A34: CONTABLE
A35: CONTROL DE GESTIÓN
A36: DATA ANALYTICS
A37: FINANZAS
A38: GESTIÓN DE CALIDAD
A39: IMPUESTOS
A40: PLANIFICACIÓN ESTRATÉGICA
A41: RRHH HARD
... A44: SISTEMAS
A46: Criticidad | B46: Recomendación
A47: Baja | B47: El riesgo residual es bajo. Si cree que conviene seguir controlándolo, genere una nueva fila y mantenga acciones.
A48: Media | B48: Es importante trabajar en reducir o controlar este riesgo residual. Debe generar una nueva fila con este riesgo y definir nuevas acciones para reducirlo o controlarlo.
A49: Alta | B49: El riesgo residual es alarmante. Debe generar una nueva fila y definir nuevas acciones de manera obligatoria para reducirlo o controlarlo.
A50: No eficaz | B50: La oportunidad no dió los resultados esperados, pregúntese si sigue siendo importante para la organización. Si la respuesta es sí, genere una nueva fila y proponga nuevas acciones.
